odoo/addons/sale_blanket_order_readonly_states/LICENSE
odoo/addons/sale_blanket_order_readonly_states/README.rst
odoo/addons/sale_blanket_order_readonly_states/__init__.py
odoo/addons/sale_blanket_order_readonly_states/__manifest__.py
odoo/addons/sale_blanket_order_readonly_states/images/screen.png
odoo/addons/sale_blanket_order_readonly_states/models/__init__.py
odoo/addons/sale_blanket_order_readonly_states/models/blanket_order.py
odoo/addons/sale_blanket_order_readonly_states/static/description/icon.png
odoo/addons/sale_blanket_order_readonly_states/static/description/index.html
odoo/addons/sale_blanket_order_readonly_states/tests/TEST_INSTRUCTIONS.rst
odoo/addons/sale_blanket_order_readonly_states/views/view_blanket_order_form.xml
odoo_addon_sale_blanket_order_readonly_states-16.0.1.0.0.dist-info/METADATA
odoo_addon_sale_blanket_order_readonly_states-16.0.1.0.0.dist-info/WHEEL
odoo_addon_sale_blanket_order_readonly_states-16.0.1.0.0.dist-info/top_level.txt
odoo_addon_sale_blanket_order_readonly_states-16.0.1.0.0.dist-info/RECORD
